jsonschema_to_typeddict/__init__.py
jsonschema_to_typeddict/__main__.py
jsonschema_to_typeddict/_version.py
jsonschema_to_typeddict/converter.py
jsonschema_to_typeddict-1.4.2.dist-info/licenses/LICENSE
jsonschema_to_typeddict-1.4.2.dist-info/WHEEL
jsonschema_to_typeddict-1.4.2.dist-info/METADATA
jsonschema_to_typeddict-1.4.2.dist-info/RECORD
