Metadata-Version: 2.4
Name: jsonschema_to_typeddict
Version: 1.4.2
Summary: Generates a python file with a TypedDict definition that attempts to match what is in a given JsonSchema.
Author-email: Henrique Gemignani Passos Lima <henrique@gemignani.org>
Requires-Python: >=3.10
Classifier: License :: OSI Approved :: Apache Software License
License-File: LICENSE
Requires-Dist: pytest ; extra == "test"
Requires-Dist: pytest-cov ; extra == "test"
Project-URL: Home, https://github.com/henriquegemignani/jsonschema-to-typeddict
Provides-Extra: test
